marburg_biobank/__init__.py
marburg_biobank/create.py
marburg_biobank/jupyter_venv_on_desktop.py
marburg_biobank/functools32/.gitignore
marburg_biobank/functools32/.travis.yml
marburg_biobank/functools32/ChangeLog
marburg_biobank/functools32/LICENSE
marburg_biobank/functools32/MANIFEST.in
marburg_biobank/functools32/setup.cfg
marburg_biobank/functools32/setup.py
marburg_biobank/functools32/test
marburg_biobank/functools32/test_functools32.py
marburg_biobank/functools32/test_support27.py
marburg_biobank/functools32/functools32/__init__.py
marburg_biobank/functools32/functools32/_dummy_thread32.py
marburg_biobank/functools32/functools32/functools32.py
marburg_biobank/functools32/functools32/reprlib32.py
marburg_biobank-0.156.dist-info/LICENSE.TXT
marburg_biobank-0.156.dist-info/METADATA
marburg_biobank-0.156.dist-info/WHEEL
marburg_biobank-0.156.dist-info/entry_points.txt
marburg_biobank-0.156.dist-info/top_level.txt
marburg_biobank-0.156.dist-info/zip-safe
marburg_biobank-0.156.dist-info/RECORD
