Metadata-Version: 2.1
Name: marburg-biobank
Version: 0.156
Summary: Interface code to interact with data from the Ovara.net biobank.
Home-page: http://www.ovara.net
Author: Florian Finkernagel
Author-email: finkernagel@imt.uni-marburg.de
License: MIT
Project-URL: Source, https://github.com/imtmarburg/marburg_biobank
Platform: UNKNOWN
Classifier: License :: OSI Approved :: MIT License
Classifier: Programming Language :: Python
Classifier: Programming Language :: Python :: 2.6
Classifier: Programming Language :: Python :: 2.7
Classifier: Programming Language :: Python :: 3
Classifier: Programming Language :: Python :: 3.3
Classifier: Programming Language :: Python :: 3.4
Classifier: Programming Language :: Python :: 3.5
Classifier: Programming Language :: Python :: 3.6
Classifier: Programming Language :: Python :: Implementation :: CPython
Classifier: Programming Language :: Python :: Implementation :: PyPy
Requires-Dist: fastparquet
Requires-Dist: numpy
Requires-Dist: pandas (>0.24)
Requires-Dist: requests
